rustworkx/__init__.py
rustworkx/__init__.pyi
rustworkx/py.typed
rustworkx/rustworkx.pyd
rustworkx/rustworkx.pyi
rustworkx/visit.py
rustworkx/visit.pyi
rustworkx/generators/__init__.pyi
rustworkx/visualization/__init__.py
rustworkx/visualization/graphviz.py
rustworkx/visualization/graphviz.pyi
rustworkx/visualization/matplotlib.py
rustworkx/visualization/matplotlib.pyi
rustworkx-0.16.0.dist-info/LICENSE
rustworkx-0.16.0.dist-info/METADATA
rustworkx-0.16.0.dist-info/WHEEL
rustworkx-0.16.0.dist-info/top_level.txt
rustworkx-0.16.0.dist-info/RECORD
