Metadata-Version: 2.1
Name: rustworkx
Version: 0.16.0
Summary: A python graph library implemented in Rust
Home-page: https://github.com/Qiskit/rustworkx
Author: Matthew Treinish
Author-email: mtreinish@kortar.org
License: Apache 2.0
Project-URL: Bug Tracker, https://github.com/Qiskit/rustworkx/issues
Project-URL: Source Code, https://github.com/Qiskit/rustworkx
Project-URL: Documentation, https://www.rustworkx.org/
Keywords: Networks network graph Graph Theory DAG
Classifier: License :: OSI Approved :: Apache Software License
Classifier: Intended Audience :: Developers
Classifier: Intended Audience :: Science/Research
Classifier: Programming Language :: Rust
Classifier: Programming Language :: Python :: 3 :: Only
Classifier: Programming Language :: Python :: 3.9
Classifier: Programming Language :: Python :: 3.10
Classifier: Programming Language :: Python :: 3.11
Classifier: Programming Language :: Python :: 3.12
Classifier: Programming Language :: Python :: 3.13
Classifier: Operating System :: MacOS :: MacOS X
Classifier: Operating System :: Microsoft :: Windows
Classifier: Operating System :: POSIX :: Linux
Requires-Python: >=3.9
Provides-Extra: mpl
Provides-Extra: graphviz
Provides-Extra: all
License-File: LICENSE
